pycivil/__init__.py
pycivil/settings.py
pycivil/EXAGeometry/__init__.py
pycivil/EXAGeometry/clouds.py
pycivil/EXAGeometry/geometry.py
pycivil/EXAGeometry/shapes.py
pycivil/EXAGeotechnical/__init__.py
pycivil/EXAGeotechnical/base.py
pycivil/EXAParametric/__init__.py
pycivil/EXAParametric/box.py
pycivil/EXAParametric/tube.py
pycivil/EXAStructural/__init__.py
pycivil/EXAStructural/checkable.py
pycivil/EXAStructural/codes.py
pycivil/EXAStructural/loads.py
pycivil/EXAStructural/materials.py
pycivil/EXAStructural/modeler.py
pycivil/EXAStructural/plot.py
pycivil/EXAStructural/sections.py
pycivil/EXAStructural/templateRCRect.py
pycivil/EXAStructural/templateRCRectFire.py
pycivil/EXAStructural/cheatsheets/__init__.py
pycivil/EXAStructural/cheatsheets/codeEC2Rules.py
pycivil/EXAStructural/cheatsheets/codeNTC2018Rules.py
pycivil/EXAStructural/lawcodes/__init__.py
pycivil/EXAStructural/lawcodes/codeEC211.py
pycivil/EXAStructural/lawcodes/codeEC212.py
pycivil/EXAStructural/lawcodes/codeNTC2018.py
pycivil/EXAStructural/rcgensolver/__init__.py
pycivil/EXAStructural/rcgensolver/templateRCGen.py
pycivil/EXAStructural/rcrecsolver/__init__.py
pycivil/EXAStructural/rcrecsolver/srvRcSecCheck.py
pycivil/EXAStructuralCheckable/RcsRectangular.py
pycivil/EXAStructuralCheckable/__init__.py
pycivil/EXAStructuralModel/__init__.py
pycivil/EXAStructuralModel/fe.py
pycivil/EXAUtils/EXAExceptions.py
pycivil/EXAUtils/__init__.py
pycivil/EXAUtils/dbtools.py
pycivil/EXAUtils/gmsh.py
pycivil/EXAUtils/latexCheatSheets.py
pycivil/EXAUtils/latexReportMakers.py
pycivil/EXAUtils/logging.py
pycivil/EXAUtils/math.py
pycivil/EXAUtils/models.py
pycivil/EXAUtils/report.py
pycivil/EXAUtils/solver.py
pycivil/EXAUtils/strand7PostPro.py
pycivil/EXAUtils/tables.py
pycivil/EXAUtils/ucasefe.py
pycivil/EXAUtils/validator.py
pycivil/EXAUtils/vtk.py
pycivil/templates/codeaster/template-thermal-rect.comm
pycivil/templates/codeaster/template-thermal-rect.export
pycivil/templates/latex/EngCalcPaper.tex
pycivil-0.2.14.dist-info/METADATA
pycivil-0.2.14.dist-info/WHEEL
pycivil-0.2.14.dist-info/licenses/LICENSE
pycivil-0.2.14.dist-info/RECORD
