Metadata-Version: 2.4
Name: pycivil
Version: 0.2.14
Summary: Structural Engineering Utilities
Author-email: Luigi Paone <ppc.luigi.paone@gmail.com>
License-File: LICENSE
Requires-Python: <3.13,>=3.9
Requires-Dist: adjusttext<2,>=1.3.0
Requires-Dist: code-aster-whale<0.2,>=0.1.0
Requires-Dist: gmsh<5,>=4.11.1
Requires-Dist: jinja2<4,>=3.1.2
Requires-Dist: matplotlib<4,>=3.7.2
Requires-Dist: mypy>=1.19.1
Requires-Dist: numpy<3,>=2.0.2
Requires-Dist: odfpy<2,>=1.4.0
Requires-Dist: openpyxl<4,>=3.1.5
Requires-Dist: pandas-stubs>=2.2.2.240807
Requires-Dist: pandas<3,>=2.1.0
Requires-Dist: pexpect<5,>=4.8.0
Requires-Dist: pydantic-settings<3,>=2.1.0
Requires-Dist: pymongo<5,>=4.4.1
Requires-Dist: pytest<9,>=8.4.1
Requires-Dist: python-multipart<0.0.21,>=0.0.20
Requires-Dist: pyvista<0.47,>=0.46.3
Requires-Dist: requests<3,>=2.31.0
Requires-Dist: rich<15,>=14.2.0
Requires-Dist: typing-extensions<5,>=4.11.0
Requires-Dist: vtk<10,>=9.5.2
Requires-Dist: xstrumodeler<0.0.2,>=0.0.1
